ReflectX/ReflectX.py
ReflectX/__init__.py
docs/source/conf.py
reflectx-1.0.0.dist-info/METADATA
reflectx-1.0.0.dist-info/WHEEL
reflectx-1.0.0.dist-info/top_level.txt
reflectx-1.0.0.dist-info/RECORD
