Metadata-Version: 2.4
Name: ReflectX
Version: 1.0.0
Summary: Reflected Light planet models
Home-page: https://reflectx.readthedocs.io/en/latest/
Author: Logan Pearce
Author-email: Logan Pearce <lapearce@umich.edu>
Project-URL: Documentation, https://reflectx.readthedocs.io
Project-URL: Homepage, https://reflectx.readthedocs.io
Project-URL: Repository, https://github.com/logan-pearce/ReflectX
Requires-Python: >=3.9
Requires-Dist: numpy
Requires-Dist: astropy
Requires-Dist: scipy
Requires-Dist: matplotlib
Requires-Dist: corner
Requires-Dist: h5py
Requires-Dist: xarray
Requires-Dist: h5netcdf
Dynamic: author
Dynamic: home-page
